<dc:author>Dorothy Day</dc:author>
<dc:description>To fight against war one must fight against conscription. Agrues the injusticies of such an act and states that Popes and Bishops have opposed conscription and encourages her readers to do the same. Spiritual not material weapons will defeat the enemy.</dc:description>
<dc:identifier>DDLW #21</dc:identifier>
<dc:date>1942-01-01</dc:date>
<dc:publisher>James Allaire</dc:publisher>
<dc:rights>Creative Commons Non-Commercial Share Alike 3.0</dc:rights>
<dc:language>en-US</dc:language>
<dc:relation>http://www.catholicworker.org/dorothyday/daytext.cfm?TextID=21</dc:relation>
