<dc:author>Dorothy Day</dc:author>
<dc:source>Information, 66 (March 1952):32-35.</dc:source>
<dc:description>An excerpt from the The Long Loneliness, concentrating on Dorothy's relationship with Sr. Aloysia, who instructs her in the faith and criticized her domestic abilities.</dc:description>
<dc:identifier>DDLW #88</dc:identifier>
<dc:date>1952-03-01</dc:date>
<dc:publisher>James Allaire</dc:publisher>
<dc:rights>Creative Commons Non-Commercial Share Alike 3.0</dc:rights>
<dc:language>en-US</dc:language>
<dc:relation>http://www.catholicworker.org/dorothyday/daytext.cfm?TextID=88</dc:relation>
