
<dc:title>Day After Day - February 1940</dc:title>

<dc:creator>Dorothy Day</dc:creator>
<dc:description>Visiting Catholic Worker houses in Baltimore and Philadelphia, she reflects on the part everyone plays in the whole movement and feels a sense of solidarity. Notes how they suffer from the cold in New York. Tells of a visit to the headquarters of the National Maritime Union and their fine reading room.</dc:description>
<dc:identifier>Dorothy Day Library on the Web document 354
<dc:date>1940-02-02</dc:date>
<dc:publisher>James Allaire</dc:publisher>
<dc:rights>Creative Commons Non-Commercial Share Alike 3.0</dc:rights>
<dc:language>en-US</dc:language>
<dc:relation>http://www.catholicworker.org/dorothyday</dc:relation>


