

	
	
	
	
	
<dc:title>Peter Maurin 1877-1977</dc:title>

<dc:creator>Dorothy Day</dc:creator>
<dc:description>Recounts her first meeting with Peter Maurin in 1932, his teaching style, his personal example, and his platform for the Catholic Worker: "Roundtable Discussions, Houses of Hospitality and Farming Communes--those were the three planks in Peter Maurin's platform."</dc:description>
<dc:identifier>Dorothy Day Library on the Web document 256
<dc:date>1977-05-01</dc:date>
<dc:publisher>James Allaire</dc:publisher>
<dc:rights>Creative Commons Non-Commercial Share Alike 3.0</dc:rights>
<dc:language>en-US</dc:language>
<dc:relation>http://www.catholicworker.org/dorothyday</dc:relation>


