

	
	
	
	
	
<dc:title>What Does Ammon Mean?</dc:title>

<dc:creator>Dorothy Day</dc:creator>
<dc:description>Chronicles her relationship with Ammon Hennacy, describing his character and memories of him at the Catholic Worker. Praises his pacifism, voluntary poverty, works of mercy, joy, prison experiences, and compassion. Asks for prayers for his reconversion to the Church.</dc:description>
<dc:identifier>Dorothy Day Library on the Web document 826
<dc:date>1965-06-01</dc:date>
<dc:publisher>James Allaire</dc:publisher>
<dc:rights>Creative Commons Non-Commercial Share Alike 3.0</dc:rights>
<dc:language>en-US</dc:language>
<dc:relation>http://www.catholicworker.org/dorothyday</dc:relation>


