

	
	
	
	
	
<dc:title>On Pilgrimage - January 1950</dc:title>

<dc:creator>Dorothy Day</dc:creator>
<dc:description>Tales from each stop of a long journey from New York through Cleveland, Chicago, St. Louis, Tulsa to Amarillo, Texas. Tells of many efforts at the works of mercy, learning to make rosaries, lectures, liturgies, and enduring suffering.</dc:description>
<dc:identifier>Dorothy Day Library on the Web document 606
<dc:date>1950-01-01</dc:date>
<dc:publisher>James Allaire</dc:publisher>
<dc:rights>Creative Commons Non-Commercial Share Alike 3.0</dc:rights>
<dc:language>en-US</dc:language>
<dc:relation>http://www.catholicworker.org/dorothyday</dc:relation>


